{
    "access": "org",
    "accessInformation": null,
    "appCategories": [
    ],
    "avgRating": 0,
    "banner": null,
    "commentsEnabled": true,
    "created": 1440726553000,
    "culture": "en-au",
    "description": "\n<p style=' margin-top:0px; margin-bottom:0px; margin-left:0px; margin-right:0px; -qt-block-indent:0; text-indent:0px;'>Draw graphics directly onto the graphics layer. Use the options at the top of the screen to change line colour and width.</p>\n<p style='-qt-paragraph-type:empty; margin-top:0px; margin-bottom:0px; margin-left:0px; margin-right:0px; -qt-block-indent:0; text-indent:0px;'><br /></p>\n<p style=' margin-top:0px; margin-bottom:0px; margin-left:0px; margin-right:0px; -qt-block-indent:0; text-indent:0px;'><span style=' font-family:'Helvetica Neue'; color:#454545;'><a href='http://geonet.esri.com/groups/appstudio/blog/2016/12/06/how-to-describe-our-resources-in-terms-of-difficulty-complexity-and-time-to-digest' target='_blank'>Resource Level:</a></span><span style=' font-family:'.Apple Color Emoji UI'; color:#454545;'>🍌🍌🍌</span> </p>",
    "documentation": null,
    "extent": [
    ],
    "guid": null,
    "id": "cf8d32fdfa1d45c08ecd3f42cc775b1e",
    "industries": [
    ],
    "itemControl": "admin",
    "languages": [
    ],
    "largeThumbnail": null,
    "licenseInfo": "<p style='-qt-paragraph-type:empty; margin-top:0px; margin-bottom:0px; margin-left:0px; margin-right:0px; -qt-block-indent:0; text-indent:0px;'><br /></p>",
    "listed": false,
    "modified": 1481071025000,
    "name": "cf8d32fdfa1d45c08ecd3f42cc775b1e.zip",
    "numComments": 3,
    "numRatings": 0,
    "numViews": 123,
    "owner": "appstudio_samples",
    "ownerFolder": null,
    "properties": null,
    "protected": false,
    "screenshots": [
    ],
    "size": 589380,
    "snippet": "Draw a graphic in a graphicsLayers",
    "spatialReference": null,
    "tags": [
        "AppStudio",
        "sample",
        "qml"
    ],
    "thumbnail": "thumbnail/thumbnail.png",
    "title": "Draw graphics",
    "type": "Native Application",
    "typeKeywords": [
        "API_QML",
        "App",
        "Application",
        "AppStudio",
        "Configuration",
        "Native",
        "qml"
    ],
    "url": null
}
