{
    "access": "private",
    "accessInformation": null,
    "appCategories": [
    ],
    "avgRating": 0,
    "banner": null,
    "commentsEnabled": true,
    "created": 1430201017000,
    "culture": "en-au",
    "description": "<html><head><meta name=\"qrichtext\" content=\"1\" /></head><body style=\" font-family:'.SF NS Text'; font-size:14pt; font-weight:400; font-style:normal;\">\n<p style=\" margin-top:0px; margin-bottom:0px; margin-left:0px; margin-right:0px; -qt-block-indent:0; text-indent:0px;\">Sample that demonstrates display of a legend for a dynamic map service.</p>\n<p style=\"-qt-paragraph-type:empty; margin-top:0px; margin-bottom:0px; margin-left:0px; margin-right:0px; -qt-block-indent:0; text-indent:0px;\"><br /></p>\n<p style=\"-qt-paragraph-type:empty; margin-top:0px; margin-bottom:0px; margin-left:0px; margin-right:0px; -qt-block-indent:0; text-indent:0px;\"><br /></p>\n<table border=\"0\" style=\" margin-top:0px; margin-bottom:0px; margin-left:0px; margin-right:0px;\" cellspacing=\"2\" cellpadding=\"0\">\n<tr>\n<td width=\"177\">\n<p style=\" margin-top:0px; margin-bottom:0px; margin-left:0px; margin-right:0px; -qt-block-indent:0; text-indent:0px;\">Resourse level: 🍌🍌</p></td></tr></table></body></html>",
    "documentation": null,
    "extent": [
    ],
    "guid": null,
    "id": "9b30c8bd4fb54ee2984bc0aa4fab8877",
    "industries": [
    ],
    "itemControl": "admin",
    "languages": [
    ],
    "largeThumbnail": null,
    "licenseInfo": "",
    "listed": false,
    "modified": 1430201017000,
    "name": "fe06367ac6c4466a8141bd387635dc2a.zip",
    "numComments": 0,
    "numRatings": 0,
    "numViews": 53,
    "owner": "appstudio_samples",
    "ownerFolder": null,
    "properties": null,
    "protected": false,
    "screenshots": [
    ],
    "size": 19054,
    "snippet": "Sample that demonstrates display of a legend",
    "spatialReference": null,
    "tags": [
        "qml",
        "app"
    ],
    "thumbnail": "thumbnail/thumbnail.png",
    "title": "Legend Sample",
    "type": "Code Sample",
    "typeKeywords": [
        "App",
        "Code",
        "Other",
        "Qml",
        "Sample"
    ],
    "url": null
}
