{
    "access": "public",
    "accessInformation": null,
    "appCategories": [
    ],
    "avgRating": 0,
    "banner": null,
    "commentsEnabled": true,
    "created": 1440729863000,
    "culture": "en-au",
    "description": "\n<p style=' margin-top:0px; margin-bottom:0px; margin-left:0px; margin-right:0px; -qt-block-indent:0; text-indent:0px;'>Each map includes a graphics layer with the same graphics, but the map on the left uses static rendering mode, and the map on the right uses dynamic rendering mode. A graphics layer that renders in static mode refreshes the graphics at the end of the animation, whereas a graphics layer rendering in dynamic mode refreshes throughout the animation. Each mode has its own strengths and weaknesses, depending on the number of graphics, complexity of geometry, and the device's GPU memory and power.</p>\n<p style='-qt-paragraph-type:empty; margin-top:0px; margin-bottom:0px; margin-left:0px; margin-right:0px; -qt-block-indent:0; text-indent:0px;'><br /></p>\n<p style=' margin-top:0px; margin-bottom:0px; margin-left:0px; margin-right:0px; -qt-block-indent:0; text-indent:0px;'><span style=' font-family:'><a href='http://geonet.esri.com/groups/appstudio/blog/2016/12/06/how-to-describe-our-resources-in-terms-of-difficulty-complexity-and-time-to-digest' target='_blank'>Resource Level:</a></span><span style=' font-family:'>🍌🍌</span> </p>",
    "documentation": null,
    "extent": [
    ],
    "guid": null,
    "id": "47d704f1b6c9429388429538a9a5980b",
    "industries": [
    ],
    "itemControl": "admin",
    "languages": [
    ],
    "largeThumbnail": null,
    "licenseInfo": null,
    "listed": false,
    "modified": 1481071639000,
    "name": "47d704f1b6c9429388429538a9a5980b.zip",
    "numComments": 3,
    "numRatings": 0,
    "numViews": 56,
    "orgId": "2U3NfasNQ9o9LkLt",
    "owner": "appstudio_samples",
    "ownerFolder": null,
    "properties": null,
    "protected": false,
    "screenshots": [
    ],
    "size": 24057,
    "snippet": "Shows the difference between the graphics layer in static and dynamic rendering mode.",
    "spatialReference": null,
    "tags": [
        "AppStudio",
        "sample",
        "qml",
        "render mode",
        "rendering"
    ],
    "thumbnail": "thumbnail/thumbnail.png",
    "title": "Rendering mode",
    "type": "Native Application",
    "typeKeywords": [
        "API_QML",
        "App",
        "Application",
        "AppStudio",
        "Configuration",
        "Native",
        "qml"
    ],
    "url": null
}
